setup.py
libepub/__init__.py
libepub/epub.py
libepub.egg-info/PKG-INFO
libepub.egg-info/SOURCES.txt
libepub.egg-info/dependency_links.txt
libepub.egg-info/top_level.txt