Metadata-Version: 1.0
Name: libepub
Version: 0.0.1
Summary: epub library
Home-page: http://www.laya.me
Author: kula
Author-email: kula@laya.me
License: gpl3
Platform: UNKNOWN
